<?xml version="1.0" encoding="UTF-8"?><?xml-stylesheet type='text/xsl' href='_UpgradeReport_Files/UpgradeReport.xslt'?><UpgradeLog>
<Properties><Property Name="Solution" Value="AzureServiceBusPubSub">
</Property><Property Name="Solution File" Value="C:\WorkingSet\NServiceBus\Samples\Azure\ServiceBusPubSub\AzureServiceBusPubSub.sln">
</Property><Property Name="User Options File" Value="C:\WorkingSet\NServiceBus\Samples\Azure\ServiceBusPubSub\AzureServiceBusPubSub.suo">
</Property><Property Name="Date" Value="Friday, July 27, 2012">
</Property><Property Name="Time" Value="14:19 PM">
</Property></Properties><Event ErrorLevel="0" Project="" Source="AzureServiceBusPubSub.sln" Description="File successfully backed up as C:\WorkingSet\NServiceBus\Samples\Azure\ServiceBusPubSub\Backup\AzureServiceBusPubSub.sln">
</Event><Event ErrorLevel="0" Project="" Source="AzureServiceBusPubSub.suo" Description="File successfully backed up as C:\WorkingSet\NServiceBus\Samples\Azure\ServiceBusPubSub\Backup\AzureServiceBusPubSub.suo">
</Event><Event ErrorLevel="0" Project="OrderWebSite" Source="OrderWebSite\OrderWebSite.csproj" Description="Project file successfully backed up as C:\WorkingSet\NServiceBus\Samples\Azure\ServiceBusPubSub\Backup\OrderWebSite\OrderWebSite.csproj">
</Event><Event ErrorLevel="0" Project="OrderWebSite" Source="OrderWebSite\Default.aspx.cs" Description="File successfully backed up as C:\WorkingSet\NServiceBus\Samples\Azure\ServiceBusPubSub\Backup\OrderWebSite\Default.aspx.cs">
</Event><Event ErrorLevel="0" Project="OrderWebSite" Source="OrderWebSite\Default.aspx.designer.cs" Description="File successfully backed up as C:\WorkingSet\NServiceBus\Samples\Azure\ServiceBusPubSub\Backup\OrderWebSite\Default.aspx.designer.cs">
</Event><Event ErrorLevel="0" Project="OrderWebSite" Source="OrderWebSite\Global.asax.cs" Description="File successfully backed up as C:\WorkingSet\NServiceBus\Samples\Azure\ServiceBusPubSub\Backup\OrderWebSite\Global.asax.cs">
</Event><Event ErrorLevel="0" Project="OrderWebSite" Source="OrderWebSite\MessageHandlers\LoadOrdersResponseMessageHandler.cs" Description="File successfully backed up as C:\WorkingSet\NServiceBus\Samples\Azure\ServiceBusPubSub\Backup\OrderWebSite\MessageHandlers\LoadOrdersResponseMessageHandler.cs">
</Event><Event ErrorLevel="0" Project="OrderWebSite" Source="OrderWebSite\MessageHandlers\OrderUpdatedEventHandler.cs" Description="File successfully backed up as C:\WorkingSet\NServiceBus\Samples\Azure\ServiceBusPubSub\Backup\OrderWebSite\MessageHandlers\OrderUpdatedEventHandler.cs">
</Event><Event ErrorLevel="0" Project="OrderWebSite" Source="OrderWebSite\Properties\AssemblyInfo.cs" Description="File successfully backed up as C:\WorkingSet\NServiceBus\Samples\Azure\ServiceBusPubSub\Backup\OrderWebSite\Properties\AssemblyInfo.cs">
</Event><Event ErrorLevel="0" Project="OrderWebSite" Source="OrderWebSite\Default.aspx" Description="File successfully backed up as C:\WorkingSet\NServiceBus\Samples\Azure\ServiceBusPubSub\Backup\OrderWebSite\Default.aspx">
</Event><Event ErrorLevel="0" Project="OrderWebSite" Source="OrderWebSite\Global.asax" Description="File successfully backed up as C:\WorkingSet\NServiceBus\Samples\Azure\ServiceBusPubSub\Backup\OrderWebSite\Global.asax">
</Event><Event ErrorLevel="0" Project="OrderWebSite" Source="OrderWebSite\Web.config" Description="File successfully backed up as C:\WorkingSet\NServiceBus\Samples\Azure\ServiceBusPubSub\Backup\OrderWebSite\Web.config">
</Event><Event ErrorLevel="0" Project="OrderWebSite" Source="OrderWebSite\OrderWebSite.csproj" Description="The project file does not require conversion.">
</Event><Event ErrorLevel="3" Project="OrderWebSite" Source="OrderWebSite\OrderWebSite.csproj" Description="No Conversion Required">
</Event><Event ErrorLevel="0" Project="OrderService" Source="OrderService\OrderService.csproj" Description="Project file successfully backed up as C:\WorkingSet\NServiceBus\Samples\Azure\ServiceBusPubSub\Backup\OrderService\OrderService.csproj">
</Event><Event ErrorLevel="0" Project="OrderService" Source="OrderService\EndpointInitialisation.cs" Description="File successfully backed up as C:\WorkingSet\NServiceBus\Samples\Azure\ServiceBusPubSub\Backup\OrderService\EndpointInitialisation.cs">
</Event><Event ErrorLevel="0" Project="OrderService" Source="OrderService\EndpointConfiguration.cs" Description="File successfully backed up as C:\WorkingSet\NServiceBus\Samples\Azure\ServiceBusPubSub\Backup\OrderService\EndpointConfiguration.cs">
</Event><Event ErrorLevel="0" Project="OrderService" Source="OrderService\MessageHandlers\OrderMessageHandler.cs" Description="File successfully backed up as C:\WorkingSet\NServiceBus\Samples\Azure\ServiceBusPubSub\Backup\OrderService\MessageHandlers\OrderMessageHandler.cs">
</Event><Event ErrorLevel="0" Project="OrderService" Source="OrderService\MessageHandlers\LoadOrdersMessageHandlers.cs" Description="File successfully backed up as C:\WorkingSet\NServiceBus\Samples\Azure\ServiceBusPubSub\Backup\OrderService\MessageHandlers\LoadOrdersMessageHandlers.cs">
</Event><Event ErrorLevel="0" Project="OrderService" Source="OrderService\OrderList.cs" Description="File successfully backed up as C:\WorkingSet\NServiceBus\Samples\Azure\ServiceBusPubSub\Backup\OrderService\OrderList.cs">
</Event><Event ErrorLevel="0" Project="OrderService" Source="OrderService\Properties\AssemblyInfo.cs" Description="File successfully backed up as C:\WorkingSet\NServiceBus\Samples\Azure\ServiceBusPubSub\Backup\OrderService\Properties\AssemblyInfo.cs">
</Event><Event ErrorLevel="0" Project="OrderService" Source="OrderService\Host.cs" Description="File successfully backed up as C:\WorkingSet\NServiceBus\Samples\Azure\ServiceBusPubSub\Backup\OrderService\Host.cs">
</Event><Event ErrorLevel="0" Project="OrderService" Source="OrderService\App.config" Description="File successfully backed up as C:\WorkingSet\NServiceBus\Samples\Azure\ServiceBusPubSub\Backup\OrderService\App.config">
</Event><Event ErrorLevel="0" Project="OrderService" Source="OrderService\OrderService.csproj" Description="The project file does not require conversion.">
</Event><Event ErrorLevel="3" Project="OrderService" Source="OrderService\OrderService.csproj" Description="No Conversion Required">
</Event><Event ErrorLevel="0" Project="MyMessages" Source="MyMessages\MyMessages.csproj" Description="Project file successfully backed up as C:\WorkingSet\NServiceBus\Samples\Azure\ServiceBusPubSub\Backup\MyMessages\MyMessages.csproj">
</Event><Event ErrorLevel="0" Project="MyMessages" Source="MyMessages\LoadOrdersMessage.cs" Description="File successfully backed up as C:\WorkingSet\NServiceBus\Samples\Azure\ServiceBusPubSub\Backup\MyMessages\LoadOrdersMessage.cs">
</Event><Event ErrorLevel="0" Project="MyMessages" Source="MyMessages\LoadOrdersResponseMessage.cs" Description="File successfully backed up as C:\WorkingSet\NServiceBus\Samples\Azure\ServiceBusPubSub\Backup\MyMessages\LoadOrdersResponseMessage.cs">
</Event><Event ErrorLevel="0" Project="MyMessages" Source="MyMessages\Order.cs" Description="File successfully backed up as C:\WorkingSet\NServiceBus\Samples\Azure\ServiceBusPubSub\Backup\MyMessages\Order.cs">
</Event><Event ErrorLevel="0" Project="MyMessages" Source="MyMessages\OrderMessage.cs" Description="File successfully backed up as C:\WorkingSet\NServiceBus\Samples\Azure\ServiceBusPubSub\Backup\MyMessages\OrderMessage.cs">
</Event><Event ErrorLevel="0" Project="MyMessages" Source="MyMessages\OrderStatus.cs" Description="File successfully backed up as C:\WorkingSet\NServiceBus\Samples\Azure\ServiceBusPubSub\Backup\MyMessages\OrderStatus.cs">
</Event><Event ErrorLevel="0" Project="MyMessages" Source="MyMessages\OrderUpdatedEvent.cs" Description="File successfully backed up as C:\WorkingSet\NServiceBus\Samples\Azure\ServiceBusPubSub\Backup\MyMessages\OrderUpdatedEvent.cs">
</Event><Event ErrorLevel="0" Project="MyMessages" Source="MyMessages\Properties\AssemblyInfo.cs" Description="File successfully backed up as C:\WorkingSet\NServiceBus\Samples\Azure\ServiceBusPubSub\Backup\MyMessages\Properties\AssemblyInfo.cs">
</Event><Event ErrorLevel="0" Project="MyMessages" Source="MyMessages\MyMessages.csproj" Description="The project file does not require conversion.">
</Event><Event ErrorLevel="3" Project="MyMessages" Source="MyMessages\MyMessages.csproj" Description="No Conversion Required">
</Event><Event ErrorLevel="0" Project="C:\WorkingSet\NServiceBus\Samples\Azure\ServiceBusPubSub\AzureServiceBusPubSub.ccproj" Source="AzureServiceBusPubSub.ccproj" Description="Project file successfully backed up as C:\WorkingSet\NServiceBus\Samples\Azure\ServiceBusPubSub\Backup\AzureServiceBusPubSub.ccproj">
</Event><Event ErrorLevel="0" Project="C:\WorkingSet\NServiceBus\Samples\Azure\ServiceBusPubSub\AzureServiceBusPubSub.ccproj" Source="AzureServiceBusPubSub.ccproj.user" Description="Project user file successfully backed up as C:\WorkingSet\NServiceBus\Samples\Azure\ServiceBusPubSub\Backup\AzureServiceBusPubSub.ccproj.user">
</Event><Event ErrorLevel="0" Project="C:\WorkingSet\NServiceBus\Samples\Azure\ServiceBusPubSub\AzureServiceBusPubSub.ccproj" Source="ServiceDefinition.csdef" Description="File successfully backed up as C:\WorkingSet\NServiceBus\Samples\Azure\ServiceBusPubSub\Backup\ServiceDefinition.csdef">
</Event><Event ErrorLevel="0" Project="C:\WorkingSet\NServiceBus\Samples\Azure\ServiceBusPubSub\AzureServiceBusPubSub.ccproj" Source="ServiceConfiguration.cscfg" Description="File successfully backed up as C:\WorkingSet\NServiceBus\Samples\Azure\ServiceBusPubSub\Backup\ServiceConfiguration.cscfg">
</Event><Event ErrorLevel="0" Project="C:\WorkingSet\NServiceBus\Samples\Azure\ServiceBusPubSub\AzureServiceBusPubSub.ccproj" Source="ServiceDefinition.csdef" Description="Updated ServiceConfiguration element schemaVersion attribute to '2012-05.1.7'.">
</Event><Event ErrorLevel="3" Project="C:\WorkingSet\NServiceBus\Samples\Azure\ServiceBusPubSub\AzureServiceBusPubSub.ccproj" Source="ServiceDefinition.csdef" Description="Converted">
</Event><Event ErrorLevel="0" Project="C:\WorkingSet\NServiceBus\Samples\Azure\ServiceBusPubSub\AzureServiceBusPubSub.ccproj" Source="ServiceConfiguration.cscfg" Description="Updated ServiceDefinition element schemaVersion attribute to '2012-05.1.7'.">
</Event><Event ErrorLevel="3" Project="C:\WorkingSet\NServiceBus\Samples\Azure\ServiceBusPubSub\AzureServiceBusPubSub.ccproj" Source="ServiceConfiguration.cscfg" Description="Converted">
</Event><Event ErrorLevel="0" Project="C:\WorkingSet\NServiceBus\Samples\Azure\ServiceBusPubSub\AzureServiceBusPubSub.ccproj" Source="AzureServiceBusPubSub.ccproj" Description="Upgraded ProductVersion value to 1.7.">
</Event><Event ErrorLevel="3" Project="C:\WorkingSet\NServiceBus\Samples\Azure\ServiceBusPubSub\AzureServiceBusPubSub.ccproj" Source="AzureServiceBusPubSub.ccproj" Description="Converted">
</Event><Event ErrorLevel="0" Project="C:\WorkingSet\NServiceBus\Samples\Azure\ServiceBusPubSub\AzureServiceBusPubSub.ccproj" Source="AzureServiceBusPubSub.ccproj" Description="Added UseIISExpressByDefault value 'false'.">
</Event><Event ErrorLevel="0" Project="C:\WorkingSet\NServiceBus\Samples\Azure\ServiceBusPubSub\AzureServiceBusPubSub.ccproj" Source="AzureServiceBusPubSub.ccproj" Description="Upgraded CloudExtensionsDir value to $(MSBuildExtensionsPath)\Microsoft\VisualStudio\v$(VisualStudioVersion)\Windows Azure Tools\1.7\.">
</Event></UpgradeLog>